nonebot_plugin_haha_ask/__init__.py
nonebot_plugin_haha_ask/geo_distance.py
nonebot_plugin_haha_ask-1.0.0.dist-info/LICENSE
nonebot_plugin_haha_ask-1.0.0.dist-info/METADATA
nonebot_plugin_haha_ask-1.0.0.dist-info/WHEEL
nonebot_plugin_haha_ask-1.0.0.dist-info/top_level.txt
nonebot_plugin_haha_ask-1.0.0.dist-info/RECORD
