Metadata-Version: 2.1
Name: nonebot-plugin-haha-ask
Version: 1.0.0
Summary: A plugin based on NoneBot2 to query travel information and distance between the two places.
Home-page: https://github.com/ziru-w/nonebot_plugin_haha_ask
Author: wk
License: UNKNOWN
Project-URL: Bug Tracker, https://github.com/ziru-w/nonebot_plugin_haha_ask/issues
Platform: UNKNOWN
Classifier: Programming Language :: Python :: 3
Classifier: License :: OSI Approved :: GNU General Public License v3 (GPLv3)
Classifier: Operating System :: OS Independent
Requires-Python: >=3.7
License-File: LICENSE
Requires-Dist: selenium
